kerberos_auth_proxy/__init__.py
kerberos_auth_proxy/cmd.py
kerberos_auth_proxy/kerberos.py
kerberos_auth_proxy/mitm/__init__.py
kerberos_auth_proxy/mitm/addons/__init__.py
kerberos_auth_proxy/mitm/addons/bearer_spnego.py
kerberos_auth_proxy/mitm/addons/setup.py
kerberos_auth_proxy/mitm/addons/spnego.py
kerberos_auth_proxy/mitm/hostutils.py
kerberos_auth_proxy/mitm/username.py
kerberos_auth_proxy/prepare.py
kerberos_auth_proxy/utils.py
kerberos_auth_proxy-0.1.0a25.dist-info/LICENSE
kerberos_auth_proxy-0.1.0a25.dist-info/METADATA
kerberos_auth_proxy-0.1.0a25.dist-info/WHEEL
kerberos_auth_proxy-0.1.0a25.dist-info/entry_points.txt
kerberos_auth_proxy-0.1.0a25.dist-info/RECORD
